treescript_files/__init__.py
treescript_files/__main__.py
treescript_files/argument_data.py
treescript_files/argument_parser.py
treescript_files/file_validation.py
treescript_files/input_data.py
treescript_files/line_reader.py
treescript_files/path_stack.py
treescript_files/string_validation.py
treescript_files/tree_data.py
treescript_files/tree_reader.py
treescript_files-0.2.4.dist-info/licenses/LICENSE
treescript_files-0.2.4.dist-info/METADATA
treescript_files-0.2.4.dist-info/WHEEL
treescript_files-0.2.4.dist-info/entry_points.txt
treescript_files-0.2.4.dist-info/top_level.txt
treescript_files-0.2.4.dist-info/RECORD
